topsis_sukham_102003334/__init__.py
topsis_sukham_102003334/topsis.py
topsis_sukham_102003334-0.1.dist-info/METADATA
topsis_sukham_102003334-0.1.dist-info/WHEEL
topsis_sukham_102003334-0.1.dist-info/entry_points.txt
topsis_sukham_102003334-0.1.dist-info/top_level.txt
topsis_sukham_102003334-0.1.dist-info/RECORD
