Metadata-Version: 2.1
Name: topsis-sukham-102003334
Version: 0.1
Summary: A Python package implementing TOPSIS technique.
Home-page: UNKNOWN
Author: Sukham
Author-email: schatha_be20@thapar.edu
License: MIT
Platform: UNKNOWN
Classifier: License :: OSI Approved :: MIT License
Classifier: Programming Language :: Python :: 3
Classifier: Programming Language :: Python :: 3.7
Requires-Dist: numpy
Requires-Dist: pandas
